binharness-0.1.1.dist-info/METADATA
binharness-0.1.1.dist-info/WHEEL
binharness-0.1.1.dist-info/license_files/LICENSE
binharness/__init__.py
binharness/common/__init__.py
binharness/common/busybox.py
binharness/common/qemu.py
binharness/localenvironment.py
binharness/py.typed
binharness/agentenvironment.py
binharness/types/__init__.py
binharness/types/target.py
binharness/types/environment.py
binharness/types/io.py
binharness/types/stat.py
binharness/types/injection.py
binharness/types/process.py
binharness/types/executor.py
binharness/util.py
binharness/agentprovider.py
binharness/bootstrap/__init__.py
binharness/bootstrap/ssh.py
binharness/bootstrap/subprocess.py
binharness/bootstrap/docker.py
binharness/serialize.py
bh_agent_client/__init__.py
bh_agent_client/bh_agent_client.cpython-38-x86_64-linux-gnu.so
binharness-0.1.1.dist-info/RECORD
