Metadata-Version: 2.3
Name: binharness
Version: 0.1.1
Requires-Dist: black >=23.3.0 ; extra == 'dev'
Requires-Dist: coverage[toml] >=7.2.3 ; extra == 'dev'
Requires-Dist: docker >=7.0.0 ; extra == 'dev'
Requires-Dist: mock-ssh-server >=0.9.1 ; extra == 'dev'
Requires-Dist: mypy >=1.2.0 ; extra == 'dev'
Requires-Dist: paramiko >=3.4.0 ; extra == 'dev'
Requires-Dist: pre-commit >=3.2.2 ; extra == 'dev'
Requires-Dist: pytest >=7.3.1 ; extra == 'dev'
Requires-Dist: pytest-cov >=4.0.0 ; extra == 'dev'
Requires-Dist: pytest-mypy >=0.10.3 ; extra == 'dev'
Requires-Dist: ruff >=0.0.262 ; extra == 'dev'
Requires-Dist: types-paramiko >=3.4.0 ; extra == 'dev'
Requires-Dist: docker >=7.0.0 ; extra == 'docker'
Requires-Dist: paramiko >=3.4.0 ; extra == 'ssh'
Provides-Extra: dev
Provides-Extra: docker
Provides-Extra: ssh
License-File: LICENSE
Summary: A framework to analyze programs running in environments
Author-email: Kevin Phoenix <kevin@kphoenix.us>
Maintainer-email: Kevin Phoenix <kevin@kphoenix.us>
Requires-Python: >=3.8
Project-URL: homepage, https://github.com/twizmwazin/binharness
Project-URL: repository, https://github.com/twizmwazin/binarness.git
